{
	"module": "certbot",
	"name": "Certbot",
	"title": "HTTPS Certificate",
	"category": "Server",
	"version": "4.0.0",
	"installMethod": "apt",
	"web": false,
	"essential": false,
	"finished": true,
	"ai": false,
	"database": "",
	"github": "certbot/certbot",
	"description": "A tool to obtain certs from Let's Encrypt on your server.",
	"keywords": [
		"HTTPS",
		"SSL",
		"Certificates",
		"Automation"
	],
	"proprietary": "DigiCert CertCentral",
	"default": {
		"cmds": [
			"/usr/bin/certbot"
		]
	}
}
